literature/__init__.py
literature/actor.py
literature/card.py
literature/constants.py
literature/knowledge.py
literature/learning.py
literature/literature.py
literature/move.py
literature/player.py
literature/test_game.py
literature/test_player.py
literature/util.py
literature-1.0.0.dist-info/licenses/LICENSE.txt
literature-1.0.0.dist-info/METADATA
literature-1.0.0.dist-info/WHEEL
literature-1.0.0.dist-info/top_level.txt
literature-1.0.0.dist-info/RECORD
