Metadata-Version: 2.4
Name: literature
Version: 1.0.0
Summary: Literature card game implementation
Home-page: https://github.com/neelsomani/literature
Download-URL: https://github.com/neelsomani/literature/releases
Author: Neel Somani
Author-email: neeljaysomani@gmail.com
License: MIT
Keywords: machine-learning,q-learning,neural-network,artificial-intelligence,card-game
Classifier: Development Status :: 5 - Production/Stable
Classifier: Intended Audience :: Developers
Classifier: Topic :: Games/Entertainment
Classifier: License :: OSI Approved :: MIT License
Classifier: Programming Language :: Python
Classifier: Programming Language :: Python :: 3
Classifier: Programming Language :: Python :: 3 :: Only
Classifier: Programming Language :: Python :: 3.9
Classifier: Programming Language :: Python :: 3.10
Classifier: Programming Language :: Python :: 3.11
Classifier: Programming Language :: Python :: 3.12
Requires-Python: >=3.9
License-File: LICENSE.txt
Requires-Dist: numpy>=1.24
Requires-Dist: scikit-learn>=1.4
Provides-Extra: dev
Requires-Dist: pytest>=7.4; extra == "dev"
Dynamic: author
Dynamic: author-email
Dynamic: classifier
Dynamic: description
Dynamic: description-content-type
Dynamic: download-url
Dynamic: home-page
Dynamic: keywords
Dynamic: license
Dynamic: license-file
Dynamic: provides-extra
Dynamic: requires-dist
Dynamic: requires-python
Dynamic: summary
